zart/__init__.py
zart/cli.py
zart/lib.py
zart-0.0.1.dist-info/METADATA
zart-0.0.1.dist-info/WHEEL
zart-0.0.1.dist-info/entry_points.txt
zart-0.0.1.dist-info/RECORD
