Metadata-Version: 2.4
Name: zart
Version: 0.0.1
Summary: Zarr command line tools
Author-email: Lukas Kluft <lukas.kluft@mpimet.mpg.de>
Requires-Python: >=3.11
Requires-Dist: click>=8.1.8
Requires-Dist: fsspec
Requires-Dist: zarr
